cronitor/__init__.py
cronitor/__main__.py
cronitor/celery.py
cronitor/monitor.py
cronitor/tests/__init__.py
cronitor/tests/test_00.py
cronitor/tests/test_config.py
cronitor/tests/test_integration.py
cronitor/tests/test_monitor.py
cronitor/tests/test_pings.py
cronitor-4.9.0.dist-info/LICENSE
cronitor-4.9.0.dist-info/METADATA
cronitor-4.9.0.dist-info/WHEEL
cronitor-4.9.0.dist-info/entry_points.txt
cronitor-4.9.0.dist-info/top_level.txt
cronitor-4.9.0.dist-info/RECORD
