Metadata-Version: 2.1
Name: cronitor
Version: 4.9.0
Summary: A lightweight Python client for Cronitor.
Home-page: https://github.com/cronitorio/cronitor-python
Author: August Flanagan
Author-email: august@cronitor.io
License: MIT License
Platform: UNKNOWN
License-File: LICENSE
Requires-Dist: requests
Requires-Dist: pyyaml
Requires-Dist: humanize
Requires-Dist: urllib3
